{
  "title": "Magic_Rock_Candy",
  "source": "stardewvalleywiki",
  "sections": [
    {
      "heading": "Introduction",
      "content": "Magic Rock Candy is a special edible item that can be obtained in variety of ways."
    },
    {
      "heading": "Locations",
      "content": "- Dropped by Haunted Skulls (0.13% chance).\n- Opening Mystery Boxes (0.2% chance) or Golden Mystery Boxes (0.4% chance).\n- One can be purchased each Thursday from the Desert Trader for 3 Prismatic Shards .\n- Can be purchased from the Raccoon Wife's Shop for 20 Golden Mystery Boxes after the 6th Raccoon family request is completed and Foraging Mastery has been claimed.\n- As the reward for donating 90 items to the Museum .\n- As the 22nd item received from the prize machine in Lewis 's manor .\n- One is sold by the Calico Egg Merchant for data-sort-value=\"250\"> 250 Calico Eggs on the last day of the Desert Festival .\n- One is sold by Jas for data-sort-value=\"300\"> 300 Calico Eggs whenever she is hosting a shop at the Desert Festival .\n- One is rewarded for submitting an Egg Rating of 55-999 to Gil during the Desert Festival."
    },
    {
      "heading": "Bundles",
      "content": "Magic Rock Candy is not used in any bundles ."
    },
    {
      "heading": "Tailoring",
      "content": "Magic Rock Candy is used in the spool of the Sewing Machine to create the prismatic Magic Sprinkle Shirt ."
    },
    {
      "heading": "Quests",
      "content": "Magic Rock Candy is not used in any quests ."
    },
    {
      "heading": "Notes",
      "content": "- Though it cannot be cooked, its underlying category in the game's data files is \"Cooking\", so Magic Rock Candy shows up on the \"Cooked Items\" tab of the Gift Log on the Social tab in-game after giving it as a gift.\n- Because it is a \"cooked\" item, it cannot be added to the Luau soup."
    },
    {
      "heading": "History",
      "content": "- 1.4 : Introduced.\n- 1.4.1 : The Desert Trader now only sells one Magic Rock Candy each Thursday.\n- 1.6 : Now obtainable at the Desert Festival . Added as possible prize from Mystery Boxes and Golden Mystery Boxes .\n- 1.6.4 : Can be obtained by trading Golden Mystery Boxes at the Giant Stump ."
    }
  ],
  "tables": [
    {
      "section": "Introduction",
      "table": {
        "headers": [],
        "rows": [
          [
            "Magic Rock Candy"
          ],
          [
            ""
          ],
          [
            "A rare and powerful candy infused with the essence of the prismatic shard."
          ],
          [
            "Information"
          ],
          [
            "Source",
            "Desert Trader, Haunted Skull, drop (0.13%), Desert Festival, Mystery Box, (0.2%), Golden Mystery Box, (0.4%), Raccoon Wife's Shop"
          ],
          [
            "Buff(s)",
            "Mining, (+2), Luck, (+5), Speed, (+1), Defense, (+5), Attack, (+5)"
          ],
          [
            "Buff Duration",
            "8m 24s"
          ],
          [
            "Energy, /, Health",
            "500, 225",
            "",
            "500",
            "",
            "225"
          ],
          [
            "",
            "500",
            "",
            "225"
          ],
          [
            "Sell Price",
            "data-sort-value=\"5000\">, 5,000g"
          ]
        ]
      }
    },
    {
      "section": "Introduction",
      "table": {
        "headers": [],
        "rows": [
          [
            "",
            "500",
            "",
            "225"
          ]
        ]
      }
    },
    {
      "section": "Gifting",
      "table": {
        "headers": [
          "Villager Reactions"
        ],
        "rows": [
          [
            "Villager Reactions"
          ],
          [
            "Love",
            "Abigail, •, Alex, •, Caroline, •, Clint, •, Demetrius, •, Dwarf, •, Elliott, •, Emily, •, Evelyn, •, George, •, Gus, •, Haley, •, Harvey, •, Jas, •, Jodi, •, Kent, •, Krobus, •, Leah, •, Leo, •, Lewis, •, Linus, •, Marnie, •, Maru, •, Pam, •, Penny, •, Pierre, •, Robin, •, Sam, •, Sandy, •, Sebastian, •, Shane, •, Vincent, •, Willy, •, Wizard"
          ]
        ]
      }
    }
  ]
}